gost_utils/__init__.py
gost_utils/currency.py
gost_utils/data.py
gost_utils/utils.py
gost_utils-0.1.7.dist-info/METADATA
gost_utils-0.1.7.dist-info/WHEEL
gost_utils-0.1.7.dist-info/top_level.txt
gost_utils-0.1.7.dist-info/RECORD
